iftg/__init__.py
iftg/image_font_manager.py
iftg/adders/__init__.py
iftg/adders/directory_noise_adder.py
iftg/adders/image_noise_adder.py
iftg/adders/noise_adder.py
iftg/creators/__init__.py
iftg/creators/creator.py
iftg/creators/image_creator.py
iftg/generators/__init__.py
iftg/generators/batches_images_generator.py
iftg/generators/generator.py
iftg/generators/images_generator.py
iftg/noises/__init__.py
iftg/noises/blur_noise.py
iftg/noises/brightness_noise.py
iftg/noises/dilate_noise.py
iftg/noises/elastic_noise.py
iftg/noises/erode_noise.py
iftg/noises/flip_noise.py
iftg/noises/gaussian_noise.py
iftg/noises/noise.py
iftg/noises/pixel_dropout_noise.py
iftg/noises/pixelate_noise.py
iftg/noises/rotation_noise.py
iftg/noises/shadow_noise.py
iftg/noises/skew_noise.py
iftg-1.3.1.dist-info/LICENSE
iftg-1.3.1.dist-info/METADATA
iftg-1.3.1.dist-info/WHEEL
iftg-1.3.1.dist-info/top_level.txt
iftg-1.3.1.dist-info/RECORD
