Metadata-Version: 2.1
Name: iftg
Version: 1.3.1
Summary: IFTG (ImageFromTextGenerator) is a Python package that simplifies creating robust datasets for OCR models. Generate images from text, apply over 10 built-in noise effects, and customize fonts and layouts. IFTG supports all languages and offers endless noise combinations, including custom noise creation.
Home-page: https://omarsamirz.github.io/ImageFromTextGenerator/
Author: Omar Samir
Author-email: omarsamir1300@gmail.com
License: MIT
Project-URL: Source, https://github.com/OmarSamirz/ImageFromTextGenerator/tree/main
Classifier: Development Status :: 4 - Beta
Classifier: Intended Audience :: Developers
Classifier: Programming Language :: Python :: 3.10
Classifier: Programming Language :: Python :: 3.11
Classifier: Programming Language :: Python :: 3.12
Classifier: Operating System :: Microsoft :: Windows
Classifier: Operating System :: POSIX :: Linux
Classifier: Operating System :: MacOS :: MacOS X
Requires-Python: >=3.10,<3.13
License-File: LICENSE
Requires-Dist: numpy>=2.1.1
Requires-Dist: opencv-python>=4.10.0.84
Requires-Dist: pillow>=10.4.0
Requires-Dist: scipy>=1.14.1
Requires-Dist: typing-extensions>=4.10.0
Requires-Dist: tqdm>=4.67.1
